qrpc/__init__.py
qrpc/client.py
qrpc/exceptions.py
qrpc/handler.py
qrpc/job.py
qrpc/methods.py
qrpc/request.py
qrpc/response.py
qrpc/result.py
qrpc/scheduler.py
qrpc/server.py
qrpc/middleware/__init__.py
qrpc/middleware/common.py
qrpc/middleware/deprecated.py
qrpc-0.1.0.dist-info/DESCRIPTION.rst
qrpc-0.1.0.dist-info/METADATA
qrpc-0.1.0.dist-info/RECORD
qrpc-0.1.0.dist-info/WHEEL
qrpc-0.1.0.dist-info/metadata.json
qrpc-0.1.0.dist-info/top_level.txt
