Metadata-Version: 2.0
Name: qrpc
Version: 0.1.0
Summary: A Python RPC Framework
Home-page: https://github.com/oangeor/qrpc
Author: chuncheng
Author-email: ischuncheng@gmail.com
License: MIT
Keywords: rpc
Platform: UNKNOWN
Classifier: Development Status :: 3 - Alpha
Classifier: License :: OSI Approved :: MIT License
Classifier: Programming Language :: Python :: 2
Classifier: Programming Language :: Python :: 2.7
Classifier: Programming Language :: Python :: 3
Requires-Dist: falcon (>=1.2.0)
Requires-Dist: requests (>=2.18.4)
Requires-Dist: six (>=1.10.0)
